lens_v1/__init__.py
lens_v1-0.1.0.dist-info/METADATA
lens_v1-0.1.0.dist-info/WHEEL
lens_v1-0.1.0.dist-info/top_level.txt
lens_v1-0.1.0.dist-info/RECORD
